setup.py
geoplotlib/__init__.py
geoplotlib/colors.py
geoplotlib/core.py
geoplotlib/layers.py
geoplotlib/utils.py
geoplotlib.egg-info/PKG-INFO
geoplotlib.egg-info/SOURCES.txt
geoplotlib.egg-info/dependency_links.txt
geoplotlib.egg-info/pbr.json
geoplotlib.egg-info/top_level.txt