Metadata-Version: 1.0
Name: geoplotlib
Version: 0.3.0
Summary: python toolbox for geographic visualizations
Home-page: https://github.com/andrea-cuttone/geoplotlib
Author: Andrea Cuttone
Author-email: andreacuttone@gmail.com
License: UNKNOWN
Platform: UNKNOWN
